sleepens/__init__.py
sleepens/main.py
sleepens/analysis/__init__.py
sleepens/analysis/_confusion_matrix.py
sleepens/analysis/_report.py
sleepens/io/__init__.py
sleepens/io/_dataobject.py
sleepens/io/_dataset.py
sleepens/io/interfaces/__init__.py
sleepens/io/interfaces/smrMAT.py
sleepens/io/interfaces/son.py
sleepens/io/interfaces/xls.py
sleepens/ml/__init__.py
sleepens/ml/_base_model.py
sleepens/ml/_cv.py
sleepens/ml/models/__init__.py
sleepens/ml/models/_gb.py
sleepens/ml/models/_stsens.py
sleepens/ml/models/_tsens.py
sleepens/postprocess/__init__.py
sleepens/postprocess/_min_rem.py
sleepens/postprocess/_rem_drop.py
sleepens/postprocess/_rem_sensitivity.py
sleepens/postprocess/_transition_fix.py
sleepens/postprocess/_wake_max.py
sleepens/postprocess/_wake_sensitivity.py
sleepens/postprocess/_wake_to_rem.py
sleepens/process/__init__.py
sleepens/process/primary/__init__.py
sleepens/process/primary/_epoched_variance.py
sleepens/process/primary/_fft.py
sleepens/process/primary/_percentile_mean.py
sleepens/process/primary/_rms.py
sleepens/process/secondary/__init__.py
sleepens/process/secondary/_merge.py
sleepens/process/secondary/_ratio.py
sleepens/process/secondary/_spectral_band.py
sleepens/process/secondary/_spectral_entropy.py
sleepens/process/secondary/_transform.py
sleepens/protocols/__init__.py
sleepens/protocols/sleepens4/__init__.py
sleepens/protocols/sleepens4/params.py
sleepens/protocols/sleepens4/processor.py
sleepens/protocols/sleepens4/sleepens4.py
sleepens/utils/__init__.py
sleepens/utils/_calculate.py
sleepens/utils/_check.py
sleepens/utils/_data_mgmt.py
sleepens/utils/_misc.py
sleepens/utils/_random.py
sleepens/utils/data/__init__.py
sleepens/utils/data/normalize.py
sleepens/utils/data/sampling.py
sleepens/utils/data/signal.py
sleepens/utils/data/smooth.py
sleepens/utils/data/transform.py
sleepens-1.0.3.dist-info/LICENSE
sleepens-1.0.3.dist-info/METADATA
sleepens-1.0.3.dist-info/WHEEL
sleepens-1.0.3.dist-info/top_level.txt
sleepens-1.0.3.dist-info/zip-safe
sleepens-1.0.3.dist-info/RECORD
