Metadata-Version: 2.1
Name: sleepens
Version: 1.0.3
Summary: Sleep Classification using Ensemble Classification
Home-page: http://github.com/paradoxysm/sleepens
Author: paradoxysm
Author-email: paradoxysm.dev@gmail.com
License: BSD-3-Clause
Download-URL: https://github.com/paradoxysm/sleepens/archive/1.0.3.tar.gz
Keywords: python,ml,ensemble,sleep,classification
Platform: UNKNOWN
Classifier: Development Status :: 4 - Beta
Classifier: Intended Audience :: Developers
Classifier: Natural Language :: English
Classifier: License :: OSI Approved :: BSD License
Classifier: Operating System :: OS Independent
Classifier: Programming Language :: Python
Classifier: Programming Language :: Python :: 3
Classifier: Programming Language :: Python :: 3.7
Classifier: Topic :: Software Development :: Libraries :: Python Modules
Classifier: Topic :: Scientific/Engineering :: Artificial Intelligence
Classifier: Topic :: Scientific/Engineering :: Information Analysis
Classifier: Intended Audience :: Science/Research
Requires-Python: >=3.9, <3.10
License-File: LICENSE
Requires-Dist: numpy (==1.21.6)
Requires-Dist: scikit-learn (==0.24.0)
Requires-Dist: joblib (==1.0.0)
Requires-Dist: tqd (==4.55.0)
Requires-Dist: xlrd (==2.0.1)
Requires-Dist: xlwt (==1.3.0)
Requires-Dist: sonpy (==1.7.5)
Requires-Dist: scipy (==1.7.2)
